hkfdb2
