Metadata-Version: 2.1
Name: hkfdb2
Version: 5.3.1
Summary: Hong Kong Finance Database.
Home-page: https://www.hkfdb.net
Author: Hong Kong Finance Database Team
Author-email: info@hkfdb.net
License: UNKNOWN
Platform: UNKNOWN
Classifier: Programming Language :: Python :: 3
Classifier: License :: OSI Approved :: MIT License
Classifier: Operating System :: OS Independent
License-File: LICENSE
